nfog/__init__.py
nfog/artwork/Artwork.py
nfog/artwork/__init__.py
nfog/config.py
nfog/constants.py
nfog/nfog.py
nfog/templates/Group.py
nfog/templates/Template.py
nfog/templates/__init__.py
nfog/tracks/Audio.py
nfog/tracks/BaseTrack.py
nfog/tracks/Subtitle.py
nfog/tracks/Video.py
nfog/tracks/__init__.py
nfog-1.1.0.dist-info/entry_points.txt
nfog-1.1.0.dist-info/LICENSE
nfog-1.1.0.dist-info/WHEEL
nfog-1.1.0.dist-info/METADATA
nfog-1.1.0.dist-info/RECORD
