Metadata-Version: 2.1
Name: nfog
Version: 1.1.0
Summary: Scriptable Database-Driven NFO Generator for Movies and TV.
Home-page: https://github.com/rlaphoenix/nfog
License: Apache-2.0
Keywords: python,nfo,generator,scriptable,imdb
Author: PHOENiX
Author-email: rlaphoenix@pm.me
Requires-Python: >=3.7,<4.0
Classifier: Development Status :: 1 - Planning
Classifier: Environment :: Console
Classifier: Intended Audience :: End Users/Desktop
Classifier: License :: OSI Approved :: Apache Software License
Classifier: Natural Language :: English
Classifier: Operating System :: OS Independent
Classifier: Programming Language :: Python :: 3
Classifier: Programming Language :: Python :: 3.10
Classifier: Programming Language :: Python :: 3.7
Classifier: Programming Language :: Python :: 3.8
Classifier: Programming Language :: Python :: 3.9
Classifier: Topic :: Documentation
Classifier: Topic :: Multimedia
Classifier: Topic :: Multimedia :: Video
Requires-Dist: appdirs (>=1.4.4,<2.0.0)
Requires-Dist: cinemagoer (>=2022.1.26,<2023.0.0)
Requires-Dist: click (>=8.0.3,<9.0.0)
Requires-Dist: click-default-group (>=1.2.2,<2.0.0)
Requires-Dist: jsonpickle (>=2.1.0,<3.0.0)
Requires-Dist: langcodes[data] (>=3.3.0,<4.0.0)
Requires-Dist: pyd2v (>=1.3.0,<2.0.0)
Requires-Dist: pymediainfo (>=5.1.0,<6.0.0)
Requires-Dist: requests (>=2.27.1,<3.0.0)
Requires-Dist: tmdbsimple (>=2.9.1,<3.0.0)
Project-URL: Repository, https://github.com/rlaphoenix/nfog
